jackutils/__init__.py
jackutils/activity.py
jackutils/currency_tool.py
jackutils/decorators.py
jackutils/dict_tool.py
jackutils/fomulas.py
jackutils/json_tool.py
jackutils/list_tool.py
jackutils/mycounter.py
jackutils/number_tool.py
jackutils/ph.py
jackutils/str_tool.py
jackutils/temp.py
jackutils/time_tool.py
jackutils/units.py
jackutils/water_utils.py
jackutils-0.1.5.dist-info/WHEEL
jackutils-0.1.5.dist-info/METADATA
jackutils-0.1.5.dist-info/RECORD
