Metadata-Version: 2.1
Name: jackutils
Version: 0.1.5
Summary: my own utils funcs and classes
Author: Jack Li
Author-email: lijack1@163.com
Requires-Python: >=3.8,<4.0
Classifier: Programming Language :: Python :: 3
Classifier: Programming Language :: Python :: 3.8
Classifier: Programming Language :: Python :: 3.9
Requires-Dist: pydantic (>=1.8.2,<2.0.0)
Requires-Dist: sympy (>=1.8,<2.0)
